README.md
setup.cfg
setup.py
nintorch/__init__.py
nintorch/trainer.py
nintorch/utils.py
nintorch.egg-info/PKG-INFO
nintorch.egg-info/SOURCES.txt
nintorch.egg-info/dependency_links.txt
nintorch.egg-info/requires.txt
nintorch.egg-info/top_level.txt
nintorch/compress/__init__.py
nintorch/compress/compress.py
nintorch/dataset/__init__.py
nintorch/dataset/dataset.py
nintorch/model/__init__.py
nintorch/model/model.py
nintorch/model/tools.py
nintorch/model_zoo/__init__.py
nintorch/model_zoo/model_zoo.py
nintorch/type/__init__.py
nintorch/type/type.py