Metadata-Version: 2.1
Name: nintorch
Version: 0.1
Summary: A wrapper of Pytorch
Home-page: https://github.com/ninfueng/nintorch
Author: Ninnart Fuengfusin
Author-email: ninnart.fuengfusin@yahoo.com
License: UNKNOWN
Platform: UNKNOWN
Classifier: Programming Language :: Python :: 3
Classifier: Programming Language :: Python :: 3.7
Classifier: Programming Language :: Python :: 3.8
Classifier: License :: OSI Approved :: MIT License
Requires-Python: >=3.7
